Workbook

Sheet Premissas
A1: Campo | B1: Valor | C1: Unidade | D1: Observacao
A2: Data da analise | B2: 2026-04-28 | D2: Planilha gerada com precos oficiais consultados em 2026-04-28.
A3: USD/BRL PTAX fechamento | B3: 4.97 | C3: BRL por USD | D3: Banco Central do Brasil, fechamento de 2026-04-27.
A4: Pedidos por mes | B4: 100 | C4: pedidos | D4: Valor editavel.
A5: Ticket medio | B5: 250 | C5: BRL | D5: Valor editavel.
A6: GMV mensal | B6: =B4*B5 -> 25000 | C6: BRL | D6: Faturamento bruto mensal usado nas taxas variaveis.
A7: Mix Pix | B7: 0.6 | C7: fracao | D7: Valor editavel.
A8: Mix cartao | B8: 0.35 | C8: fracao | D8: Valor editavel.
A9: Mix boleto | B9: 0.05 | C9: fracao | D9: Valor editavel.
A10: Taxa cartao MP em 30 dias | B10: 0.0399 | C10: fracao | D10: Checkout online; fonte oficial Mercado Pago.
A11: Taxa cartao MP na hora | B11: 0.0499 | C11: fracao | D11: Alternativa para comparacao de fluxo de caixa.
A12: Taxa Pix MP | B12: 0.0099 | C12: fracao | D12: Checkout online; fonte oficial Mercado Pago.
A13: Taxa boleto MP | B13: 3.49 | C13: BRL por boleto | D13: Checkout online; fonte oficial Mercado Pago.
A14: Storage R2 usado | B14: 20 | C14: GB-mes | D14: Exemplo para imagens e modelos 3D; valor editavel.
A15: Operacoes R2 Class A | B15: 0.1 | C15: milhoes/mes | D15: Exemplo; valor editavel.
A16: Operacoes R2 Class B | B16: 2 | C16: milhoes/mes | D16: Exemplo; valor editavel.
A17: Emails transacionais por mes | B17: 1500 | C17: emails | D17: Exemplo; 15 emails por 10 pedidos.
A18: Caixas Google Workspace | B18: 1 | C18: usuarios | D18: Exemplo para suporte@ ou contato@.
... A23: IOF sobre gastos internacionais | B23: 0.035 | C23: fracao | D23: Usado para estimar custo em cartao em SaaS cobrados em USD.

Sheet Custos
A1: Categoria | B1: Item | C1: Provider | D1: Status | E1: Tipo | F1: Moeda | G1: Preco unitario | H1: Quantidade / formula | I1: Mensal moeda origem | J1: Mensal em BRL | K1: Incluir no total | L1: Notas | M1: Fonte
A2: Dominio | B2: Dominio .com.br | C2: Registro.br | D2: Obrigatorio | E2: Fixo | F2: BRL | G2: 40 | H2: =1/12 -> 0.083333333 | I2: =G2*H2 -> 3.3333333 | J2: =I2 -> 3.3333333 | K2: 1 | L2: Registro anual de dominio brasileiro; mensalizado para orcamento. | M2: https://registro.br/
A3: Dominio | B3: Dominio .com (alternativa) | C3: Porkbun | D3: Alternativa | E3: Fixo | F3: USD | G3: 11.08 | H3: =1/12 -> 0.083333333 | I3: =G3*H3 -> 0.92333333 | J3: =I3*Premissas!$B$3 -> 4.5889667 | K3: 0 | L3: Alternativa internacional; use se decidir operar com .com em vez de .com.br. | M3: https://porkbun.com/products/domains
A4: Hospedagem | B4: Frontend / app Next.js - Pro | C4: Vercel | D4: Obrigatorio | E4: Fixo | F4: USD | G4: 20 | H4: 1 | I4: =G4*H4 -> 20 | J4: =I4*Premissas!$B$3 -> 99.4 | K4: 1 | L4: Plano Pro para ambiente de producao. Hobby existe, mas este orcamento usa baseline profissional. | M4: https://vercel.com/pricing
A5: Hospedagem | B5: Transferencia extra | C5: Vercel | D5: Sob demanda | E5: Overage | F5: USD | G5: 0.15 | H5: =Premissas!$B$21 -> 0 | I5: =G5*H5 -> 0 | J5: =I5*Premissas!$B$3 -> 0 | K5: 1 | L5: So cobra se passar do incluido no plano. | M5: https://vercel.com/pricing
A6: Hospedagem | B6: Edge requests extras | C6: Vercel | D6: Sob demanda | E6: Overage | F6: USD | G6: 2 | H6: =Premissas!$B$22 -> 0 | I6: =G6*H6 -> 0 | J6: =I6*Premissas!$B$3 -> 0 | K6: 1 | L6: Preco por 1M de requests acima do incluido no Pro. | M6: https://vercel.com/pricing
A7: Banco de dados | B7: Postgres gerenciado - Launch | C7: Neon | D7: Obrigatorio | E7: Fixo estimado | F7: USD | G7: 15 | H7: 1 | I7: =G7*H7 -> 15 | J7: =I7*Premissas!$B$3 -> 74.55 | K7: 1 | L7: Usa o typical spend oficial do plano Launch como baseline do projeto. | M7: https://neon.com/pricing
A8: Storage de assets | B8: Storage acima do free tier | C8: Cloudflare R2 | D8: Sob demanda | E8: Variavel | F8: USD | G8: 0.015 | H8: =MAX(0,Premissas!$B$14-10) -> 10 | I8: =G8*H8 -> 0.15 | J8: =I8*Premissas!$B$3 -> 0.7455 | K8: 1 | L8: O free tier inclui 10 GB-mes; este item cobra apenas excedente. | M8: https://developers.cloudflare.com/r2/pricing/
A9: Storage de assets | B9: Operacoes Class A acima do free tier | C9: Cloudflare R2 | D9: Sob demanda | E9: Variavel | F9: USD | G9: 4.5 | H9: =MAX(0,Premissas!$B$15-1) -> 0 | I9: =G9*H9 -> 0 | J9: =I9*Premissas!$B$3 -> 0 | K9: 1 | L9: Preco por milhao de operacoes acima de 1M/mensal. | M9: https://developers.cloudflare.com/r2/pricing/
A10: Storage de assets | B10: Operacoes Class B acima do free tier | C10: Cloudflare R2 | D10: Sob demanda | E10: Variavel | F10: USD | G10: 0.36 | H10: =MAX(0,Premissas!$B$16-10) -> 0 | I10: =G10*H10 -> 0 | J10: =I10*Premissas!$B$3 -> 0 | K10: 1 | L10: Preco por milhao de operacoes acima de 10M/mensal. | M10: https://developers.cloudflare.com/r2/pricing/
A11: Email transacional | B11: Plano Pro | C11: Resend | D11: Opcional | E11: Fixo | F11: USD | G11: 20 | H11: =Premissas!$B$20 -> 0 | I11: =G11*H11 -> 0 | J11: =I11*Premissas!$B$3 -> 0 | K11: 1 | L11: Se B20=0, voce fica no Free ate 3.000 emails/mes; se B20=1, usa Pro com 50.000 emails/mes. | M11: https://resend.com/pricing
A12: Email corporativo | B12: Business Starter | C12: Google Workspace | D12: Recomendado | E12: Fixo | F12: USD | G12: 7 | H12: =Premissas!$B$18 -> 1 | I12: =G12*H12 -> 7 | J12: =I12*Premissas!$B$3 -> 34.79 | K12: 1 | L12: Usado para caixa profissional com dominio proprio. | M12: https://workspace.google.com/pricing
A13: Monitoramento | B13: Plano Solo | C13: UptimeRobot | D13: Opcional | E13: Fixo | F13: USD | G13: 7 | H13: =Premissas!$B$19 -> 1 | I13: =G13*H13 -> 7 | J13: =I13*Premissas!$B$3 -> 34.79 | K13: 1 | L13: Monitoramento de disponibilidade e expirar de SSL/dominio. | M13: https://uptimerobot.com/pricing/
A14: Pagamentos | B14: Taxa Pix | C14: Mercado Pago | D14: Obrigatorio | E14: Variavel | F14: BRL | G14: =Premissas!$B$12 -> 0.0099 | H14: =Premissas!$B$6*Premissas!$B$7 -> 15000 | I14: =G14*H14 -> 148.5 | J14: =I14 -> 148.5 | K14: 1 | L14: Baseado no mix de Pix e na taxa online oficial. | M14: https://www.mercadopago.com.br/blog/quanto-custa-vender-on-line-com-mercado-pago
A15: Pagamentos | B15: Taxa cartao (recebendo em 30 dias) | C15: Mercado Pago | D15: Obrigatorio | E15: Variavel | F15: BRL | G15: =Premissas!$B$10 -> 0.0399 | H15: =Premissas!$B$6*Premissas!$B$8 -> 8750 | I15: =G15*H15 -> 349.125 | J15: =I15 -> 349.125 | K15: 1 | L15: Use esta linha como baseline. Se quiser comparar recebimento imediato, veja a linha abaixo. | M15: https://www.mercadopago.com.br/blog/quanto-custa-vender-on-line-com-mercado-pago
A16: Pagamentos | B16: Delta se trocar cartao para recebimento na hora | C16: Mercado Pago | D16: Cenario | E16: Variavel | F16: BRL | G16: =(Premissas!$B$11-Premissas!$B$10) -> 0.01 | H16: =Premissas!$B$6*Premissas!$B$8 -> 8750 | I16: =G16*H16 -> 87.5 | J16: =I16 -> 87.5 | K16: 0 | L16: Mantido fora do total para servir de comparacao de fluxo de caixa. | M16: https://www.mercadopago.com.br/blog/quanto-custa-vender-on-line-com-mercado-pago
A17: Pagamentos | B17: Taxa boleto | C17: Mercado Pago | D17: Obrigatorio | E17: Variavel | F17: BRL | G17: =Premissas!$B$13 -> 3.49 | H17: =Premissas!$B$4*Premissas!$B$9 -> 5 | I17: =G17*H17 -> 17.45 | J17: =I17 -> 17.45 | K17: 1 | L17: Custo por boleto emitido no mix informado. | M17: https://www.mercadopago.com.br/blog/quanto-custa-vender-on-line-com-mercado-pago
A18: Tributo financeiro | B18: IOF sobre SaaS em USD | C18: Cartao / emissor | D18: Sob demanda | E18: Variavel | F18: BRL | G18: =Premissas!$B$23*SUMPRODUCT(($F$2:$F$13="USD")*($K$2:$K$13=1)*($I$2:$I$13))*Premissas!$B$3 -> 8.5496425 | H18: 1 | I18: =G18*H18 -> 8.5496425 | J18: =I18 -> 8.5496425 | K18: 1 | L18: Estimativa do imposto em cobrancas internacionais pagas com cartao brasileiro. | M18: https://www.gov.br/fazenda/pt-br/central-de-conteudo/publicacoes/apresentacoes/2025/Maio/iof-maio-2025.pdf/%40%40download/file
A19: Infra incluida | B19: SSL/TLS | C19: Vercel / Let's Encrypt | D19: Incluido | E19: Zero | F19: USD | G19: 0 | H19: 1 | I19: =0 -> 0 | J19: =0 -> 0 | K19: 0 | L19: Nao orcado separadamente; tratado como custo zero no stack sugerido. | M19: https://vercel.com/pricing
A20: Infra incluida | B20: CDN global | C20: Vercel | D20: Incluido | E20: Zero | F20: USD | G20: 0 | H20: 1 | I20: =0 -> 0 | J20: =0 -> 0 | K20: 0 | L20: Incluso no plano; overage aparece nas linhas de transferencia e edge requests. | M20: https://vercel.com/pricing
A21: Infra incluida | B21: Backups base / time-travel | C21: Neon | D21: Incluido | E21: Zero | F21: USD | G21: 0 | H21: 1 | I21: =0 -> 0 | J21: =0 -> 0 | K21: 0 | L21: Ja contemplado no baseline do Neon Launch. | M21: https://neon.com/pricing
A22: Gateway | B22: Mensalidade do meio de pagamento | C22: Mercado Pago | D22: Incluido | E22: Zero | F22: BRL | G22: 0 | H22: 1 | I22: =0 -> 0 | J22: =0 -> 0 | K22: 0 | L22: O gateway online modelado aqui nao entra com mensalidade fixa; o custo vem das taxas por venda. | M22: https://www.mercadopago.com.br/developers/pt/support/37740

Sheet Resumo
A1: Resumo | B1: Formula / valor | C1: Observacao
A2: Custos fixos obrigatorios | B2: =SUMPRODUCT((Custos!$E$2:$E$22<>"Variavel")*(Custos!$E$2:$E$22<>"Overage")*(Custos!$D$2:$D$22="Obrigatorio")*(Custos!$K$2:$K$22=1)*Custos!$J$2:$J$22) -> 177.28333 | C2: Sem custos opcionais e sem taxas por venda.
A3: Custos fixos adicionais recomendados/opcionais ligados | B3: =SUMPRODUCT((Custos!$E$2:$E$22<>"Variavel")*(Custos!$E$2:$E$22<>"Overage")*((Custos!$D$2:$D$22="Recomendado")+(Custos!$D$2:$D$22="Opcional"))*(Custos!$K$2:$K$22=1)*Custos!$J$2:$J$22) -> 69.58 | C3: Mostra apenas o adicional acima do minimo obrigatorio.
A4: Custos variaveis do cenario atual | B4: =SUMPRODUCT((Custos!$E$2:$E$22="Variavel")*(Custos!$K$2:$K$22=1)*Custos!$J$2:$J$22) -> 524.37014 | C4: Inclui taxas de pagamento, storage variavel e IOF do cenario atual.
A5: Overages tecnicos no cenario atual | B5: =SUMPRODUCT((Custos!$E$2:$E$22="Overage")*(Custos!$K$2:$K$22=1)*Custos!$J$2:$J$22) -> 0 | C5: Normalmente zero se o uso ficar no baseline.
A6: Total mensal operacional | B6: =B2+B3+B4+B5 -> 771.23348 | C6: Soma do que entra no orcamento mensal do site.
A7: Delta se cartao receber na hora | B7: =Custos!J16 -> 87.5 | C7: Custo extra mensal se trocar o cartao de 30 dias para recebimento imediato.
A8: Total mensal com cartao na hora | B8: =B6+B7 -> 858.73348 | C8: Cenario alternativo de caixa.
A9: Observacao de escopo | B9: Fora do escopo | C9: Nao inclui custo do produto, frete do dropshipping, impostos da empresa, devolucoes, chargeback, dev e design.

Sheet Fontes
A1: Fonte | B1: URL | C1: Uso | D1: Data de acesso
A2: Registro.br | B2: https://registro.br/ | C2: Meta description com preco de dominio .br | D2: 2026-04-28
A3: Porkbun | B3: https://porkbun.com/products/domains | C3: Preco de entrada para .com | D3: 2026-04-28
A4: Vercel Pricing | B4: https://vercel.com/pricing | C4: Plano Pro e overages | D4: 2026-04-28
A5: Neon Pricing | B5: https://neon.com/pricing | C5: Typical spend e preco Launch | D5: 2026-04-28
A6: Cloudflare R2 Pricing | B6: https://developers.cloudflare.com/r2/pricing/ | C6: Storage, operacoes e free tier | D6: 2026-04-28
A7: Resend Pricing | B7: https://resend.com/pricing | C7: Free e Pro para email transacional | D7: 2026-04-28
A8: Google Workspace Pricing | B8: https://workspace.google.com/pricing | C8: Business Starter por usuario | D8: 2026-04-28
A9: UptimeRobot Pricing | B9: https://uptimerobot.com/pricing/ | C9: Plano Solo de monitoramento | D9: 2026-04-28
A10: Mercado Pago blog oficial | B10: https://www.mercadopago.com.br/blog/quanto-custa-vender-on-line-com-mercado-pago | C10: Taxas online de cartao, Pix e boleto | D10: 2026-04-28
A11: Mercado Pago support | B11: https://www.mercadopago.com.br/developers/pt/support/37740 | C11: Confirmacao de que o custo varia por meio e prazo | D11: 2026-04-28
A12: BCB PTAX | B12: https://olinda.bcb.gov.br/olinda/servico/PTAX/versao/v1/odata/CotacaoMoedaPeriodo | C12: Conversao USD/BRL usada na planilha | D12: 2026-04-28
A13: Gov.br Fazenda | B13: https://www.gov.br/fazenda/pt-br/central-de-conteudo/publicacoes/apresentacoes/2025/Maio/iof-maio-2025.pdf/%40%40download/file | C13: Aliquota de 3,5% para cartoes internacionais | D13: 2026-04-28
